tests/__init__.py
meowmeowutils-0.1.0.dist-info/METADATA
meowmeowutils-0.1.0.dist-info/WHEEL
meowmeowutils-0.1.0.dist-info/top_level.txt
meowmeowutils-0.1.0.dist-info/RECORD
