Metadata-Version: 2.4
Name: meowmeowutils
Version: 0.1.0
Home-page: https://github.com/JetpackYoshi/meowmeowutils
Author: Yoshika Govender
Author-email: Yoshika Govender <yoshi.govender@gmail.com>
Project-URL: Homepage, https://github.com/JetpackYoshi/meowmeow
Keywords: file tools
Classifier: Development Status :: 2 - Pre-Alpha
Requires-Python: >=3.10
Dynamic: author
Dynamic: home-page
Dynamic: requires-python
